{
  "generated_at": "2026-06-25T18:35:29.006496+08:00",
  "total_titles_processed": 311,
  "failed_sources": [],
  "trends": [
    {
      "keyword_group": "伊朗",
      "match_count": 6,
      "ai_insight": {
        "analysis": "该板块当前收录 6 条热点，覆盖 4 个来源平台，平均热榜排名约 12.3 位，标题平均出现 1.0 次。",
        "prediction": "未来6-12小时内热度可能逐步回落，新增驱动偏弱，建议以观察延续性为主，避免过度追高。",
        "direction": "回落",
        "confidence": 83,
        "chart": []
      },
      "titles": [
        {
          "title": "鲁比奥称美国不会不惜一切代价同伊朗达成协议",
          "url": "https://wallstreetcn.com/livenews/3124607",
          "source": "华尔街见闻-快讯",
          "ranks": [
            2
          ],
          "is_new": false,
          "appearance_count": 1,
          "time_info": "18时35分"
        },
        {
          "title": "美飞行员曝伊朗「创新武器」，简直是外星来的东西，具体情况如何？伊朗无人机研发是什么水平？",
          "url": "https://www.zhihu.com/question/2053109056487822677",
          "source": "知乎",
          "ranks": [
            6
          ],
          "is_new": false,
          "appearance_count": 1,
          "time_info": "18时35分"
        },
        {
          "title": "伊朗石油部长：伊朗愿在金砖国家能源合作中发挥积极作用。",
          "url": "https://flash.jin10.com/detail/20260625175721071800",
          "source": "金十数据",
          "ranks": [
            13
          ],
          "is_new": false,
          "appearance_count": 1,
          "time_info": "18时35分"
        },
        {
          "title": "伊朗石油部长：正如伊朗一再指出的那样，要实现为世界提供大量能源的西亚地区的稳定与安全，唯一途径就是让外国势力撤出该地区，拆除美国军事基地，并将安全事务移交给该地区各国。",
          "url": "https://flash.jin10.com/detail/20260625175624324800",
          "source": "金十数据",
          "ranks": [
            15
          ],
          "is_new": false,
          "appearance_count": 1,
          "time_info": "18时35分"
        },
        {
          "title": "伊朗石油部官方网站Shana：伊朗石油部长帕克内贾德在金砖国家能源会议间隙与印度同行就能源合作及恰巴哈尔港事宜进行磋商。",
          "url": "https://flash.jin10.com/detail/20260625175447099800",
          "source": "金十数据",
          "ranks": [
            17
          ],
          "is_new": false,
          "appearance_count": 1,
          "time_info": "18时35分"
        },
        {
          "title": "世界杯生死战前伊朗队被迫滞留机场",
          "url": "https://www.toutiao.com/trending/7655006558115512326/",
          "source": "今日头条",
          "ranks": [
            21
          ],
          "is_new": false,
          "appearance_count": 1,
          "time_info": "18时35分"
        }
      ]
    },
    {
      "keyword_group": "特朗普",
      "match_count": 4,
      "ai_insight": {
        "analysis": "该板块当前收录 4 条热点，覆盖 4 个来源平台，平均热榜排名约 7.2 位，标题平均出现 1.0 次。",
        "prediction": "未来6-12小时内热度可能逐步回落，新增驱动偏弱，建议以观察延续性为主，避免过度追高。",
        "direction": "回落",
        "confidence": 77,
        "chart": []
      },
      "titles": [
        {
          "title": "特朗普：对意法德英很失望，希望北约盟友表忠心",
          "url": "https://news.ifeng.com/c/8uFCJ6kPTr8",
          "source": "凤凰网",
          "ranks": [
            3
          ],
          "is_new": false,
          "appearance_count": 1,
          "time_info": "18时35分"
        },
        {
          "title": "再度呼吁降息！特朗普回应拒签住房法案：低利率能解决一切",
          "url": "https://www.cls.cn/detail/2408936",
          "source": "财联社热门",
          "ranks": [
            5
          ],
          "is_new": false,
          "appearance_count": 1,
          "time_info": "18时35分"
        },
        {
          "title": "特朗普炮轰石油公司“宰客”：汽油价格降得太慢太少，要求司法部调查",
          "url": "https://m.thepaper.cn/newsDetail_forward_33445001",
          "source": "澎湃新闻",
          "ranks": [
            8
          ],
          "is_new": false,
          "appearance_count": 1,
          "time_info": "18时35分"
        },
        {
          "title": "国际足联主席确认特朗普将出席世界杯决赛，并直接向冠军球队颁奖，如何看待这一操作？为啥会打破惯例？",
          "url": "https://www.zhihu.com/question/2053130730595791572",
          "source": "知乎",
          "ranks": [
            13
          ],
          "is_new": false,
          "appearance_count": 1,
          "time_info": "18时35分"
        }
      ]
    },
    {
      "keyword_group": "金价",
      "match_count": 3,
      "ai_insight": {
        "analysis": "该板块当前收录 3 条热点，覆盖 3 个来源平台，平均热榜排名约 15.7 位，标题平均出现 1.0 次。",
        "prediction": "未来6-12小时内热度可能逐步回落，新增驱动偏弱，建议以观察延续性为主，避免过度追高。",
        "direction": "回落",
        "confidence": 82,
        "chart": []
      },
      "titles": [
        {
          "title": "金价大跌投资者抄底刷爆银行卡 金店10克20克金条3小时卖光",
          "url": "https://wallstreetcn.com/livenews/3124603",
          "source": "华尔街见闻-快讯",
          "ranks": [
            4
          ],
          "is_new": false,
          "appearance_count": 1,
          "time_info": "18时35分"
        },
        {
          "title": "现货黄金价格跌破4000美元大关",
          "url": "https://m.thepaper.cn/newsDetail_forward_33446112",
          "source": "澎湃新闻",
          "ranks": [
            18
          ],
          "is_new": false,
          "appearance_count": 1,
          "time_info": "18时35分"
        },
        {
          "title": "金价跌回3字头、半年回撤30%，牛市终结还是深度调整？",
          "url": "https://flash.jin10.com/detail/20260625174955903800",
          "source": "金十数据",
          "ranks": [
            25
          ],
          "is_new": false,
          "appearance_count": 1,
          "time_info": "18时35分"
        }
      ]
    },
    {
      "keyword_group": "美股",
      "match_count": 2,
      "ai_insight": {
        "analysis": "该板块当前收录 2 条热点，覆盖 1 个来源平台，平均热榜排名约 5.0 位，标题平均出现 1.0 次。",
        "prediction": "未来6-12小时内热度可能逐步回落，新增驱动偏弱，建议以观察延续性为主，避免过度追高。",
        "direction": "回落",
        "confidence": 71,
        "chart": []
      },
      "titles": [
        {
          "title": "SpaceX美股盘前扩大涨势，现上涨2.4%。",
          "url": "https://wallstreetcn.com/livenews/3124608",
          "source": "华尔街见闻-快讯",
          "ranks": [
            1
          ],
          "is_new": false,
          "appearance_count": 1,
          "time_info": "18时35分"
        },
        {
          "title": "IBM美股盘前涨超6%，公司推出全球首款亚1纳米芯片技术",
          "url": "https://wallstreetcn.com/livenews/3124593",
          "source": "华尔街见闻-快讯",
          "ranks": [
            9
          ],
          "is_new": false,
          "appearance_count": 1,
          "time_info": "18时35分"
        }
      ]
    }
  ],
  "report_image_url": "https://joyce677.github.io/TrendRadar/img/news.jpg"
}